Metadata-Version: 2.1
Name: solidity-grammar-parser
Version: 0.0.2
Summary: Solidity ANTLR4 grammar Python parser
Author-email: Georgii Plotnikov <accembler@gmail.com>
Project-URL: Homepage, https://github.com/OpenZeppelin/sgp
Project-URL: Bug Tracker, https://github.com/OpenZeppelin/sgp/issues
Classifier: Programming Language :: Python :: 3
Classifier: License :: OSI Approved :: MIT License
Classifier: Operating System :: OS Independent
Requires-Python: >=3.10
License-File: LICENSE
Requires-Dist: antlr4-python3-runtime ==4.13.1
Requires-Dist: coverage ==7.3.1
Requires-Dist: simplejson ==3.19.1
Requires-Dist: typing ==3.7.4.3
Requires-Dist: typing-extensions ==4.8.0
